{"name":"Photon-HDF5 reading examples","tagline":"Code examples of reading Photon-HDF5 files in multiple laguages","body":"# Photon-HDF5 Reading Examples\r\n\r\nThis repository contains code examples on reading [Photon-HDF5](http://photon-hdf5.org/) files in multiple languages.\r\n\r\nEach folder contain examples for a specific language (Python, MATLAB or LabVIEW).\r\nFor python, we provide both [notebooks](http://nbviewer.ipython.org/github/Photon-HDF5/photon_hdf5_reading_examples/blob/master/python/Reading%20%C2%B5s-ALEX%20data%20from%20Photon-HDF5.ipynb) and scripts.\r\n\r\nTo execute the examples please download this repository archive\r\n([Download ZIP](https://github.com/Photon-HDF5/photon_hdf5_reading_examples/archive/master.zip))\r\nand extract it: it will contain an empty data folder. Next, download the\r\n[example Photon-HDF5 files](http://figshare.com/articles/Example_smFRET_data_files_in_Photon_HDF5_format/1456362)\r\nand unzip them in the empty data folder.\r\n\r\nFor more info on reading Photon-HDF5 files refer to the official [Photon-HDF5 documentation](http://photon-hdf5.readthedocs.org/), in particular:\r\n\r\n- [Reading Photon-HDF5 files](http://photon-hdf5.readthedocs.org/en/latest/reading.html)\r\n\r\n\r\n## Support\r\n\r\nFor any issue in running the examples please [open an issue](https://github.com/Photon-HDF5/photon_hdf5_reading_examples/issues) or ask a question on the [Photon-HDF5 Google Group](https://groups.google.com/forum/#!forum/photon-hdf5).\r\n","google":"","note":"Don't delete this file! It's used internally to help with page regeneration."}